semvergen/__init__.py
semvergen/_version.py
semvergen/generate.py
semvergen/bin/semvergen
semvergen/tests/__init__.py
semvergen/tests/conftest.py
semvergen/tests/test_generate.py
semvergen-0.1.8.data/data/Pipfile.lock
semvergen-0.1.8.data/scripts/semvergen
semvergen-0.1.8.dist-info/METADATA
semvergen-0.1.8.dist-info/WHEEL
semvergen-0.1.8.dist-info/top_level.txt
semvergen-0.1.8.dist-info/RECORD
